shurjopay_v2/__init__.py
shurjopay_v2/callbackHandler.py
shurjopay_v2/shurjopay.py
shurjopay_V2-0.0.3.dist-info/LICENSE
shurjopay_V2-0.0.3.dist-info/METADATA
shurjopay_V2-0.0.3.dist-info/WHEEL
shurjopay_V2-0.0.3.dist-info/top_level.txt
shurjopay_V2-0.0.3.dist-info/RECORD
