Metadata-Version: 2.1
Name: shurjopay-V2
Version: 0.0.3
Summary: shurjopay version 2 payment gateway integration package for python users.
Home-page: https://github.com/shurjoPay-Plugins/Python.git
Author: Mohammad Jayeed
Author-email: jayeed@pranisheba.com.bd
Project-URL: Bug Tracker, https://github.com/shurjoPay-Plugins/Python
Classifier: Programming Language :: Python :: 3
Classifier: License :: OSI Approved :: MIT License
Classifier: Operating System :: OS Independent
Requires-Python: >=3.6
License-File: LICENSE
Requires-Dist: requests
